imagetk/__init__.py
imagetk/assess.cp312-win_amd64.pyd
imagetk/dedup.cp312-win_amd64.pyd
imagetk/dedup.py
imagetk/edge.cp312-win_amd64.pyd
imagetk/feature.cp312-win_amd64.pyd
imagetk/kernel.cp312-win_amd64.pyd
imagetk/process.cp312-win_amd64.pyd
imagetk/threshold.cp312-win_amd64.pyd
imagetk-0.1.3.dist-info/METADATA
imagetk-0.1.3.dist-info/WHEEL
imagetk-0.1.3.dist-info/top_level.txt
imagetk-0.1.3.dist-info/RECORD
