Metadata-Version: 2.1
Name: imagetk
Version: 0.1.3
Summary: image toolkit
Author: 
Author-email: 
Keywords: image
Platform: any
Requires-Python: >=3.10
Requires-Dist: numpy >=1.14.0
Requires-Dist: pandas >=2.2.0
Requires-Dist: scipy >=1.0.0
Requires-Dist: scient >=0.5.0
